Midterm/exam4_assign.v
module exam4(a, b, c, f);
    input a, b, c;
    output f;

    assign f = !a & b & !c | a & !b | !b & c;
endmodule

module t_exam4;
    reg a, b, c;
    wire f;
    exam4 E1(a, b, c, f);

    initial begin
	    $dumpfile("exam4.vcd");
	    $dumpvars(0, t_exam4);
        a = 1'b0; b = 1'b0; c = 1'b0;
        #1 a = 1'b0; b = 1'b0; c = 1'b1;
        #1 a = 1'b0; b = 1'b1; c = 1'b0;
        #1 a = 1'b0; b = 1'b1; c = 1'b1;
        #1 a = 1'b1; b = 1'b0; c = 1'b0;
        #1 a = 1'b1; b = 1'b0; c = 1'b1;
        #1 a = 1'b1; b = 1'b1; c = 1'b0;
        #1 a = 1'b1; b = 1'b1; c = 1'b1;
    end
    
    initial $monitor("time=%02d, {a,b,c}=%b%b%b, f=%b", $time, a, b, c, f);
endmodule

Midterm/build/exam4.vcd
$date
	Fri Dec 09 14:02:04 2022
$end
$version
	Icarus Verilog
$end
$timescale
	1s
$end
$scope module t_exam4 $end
$var wire 1 ! f $end
$var reg 1 " a $end
$var reg 1 # b $end
$var reg 1 $ c $end
$upscope $end
$enddefinitions $end
#0
$dumpvars
0$
0#
0"
0!
$end
#1
1!
1$
#2
0$
1#
#3
0!
1$
#4
1!
0$
0#
1"
#5
1$
#6
0!
0$
1#
#7
1$
