LAB08/D_latch.v
module D_latch (D, enable, Q);
  input D, enable;
  output Q;
  reg Q;

  always @(D or enable)
  begin
    if(enable == 1)
      Q = D;
  end

endmodule

LAB08/t_D_latch.v
`include "D_latch.v"
module t_D_latch ();
  reg D, enable;
  wire Q;
  D_latch L1(D, enable, Q);

  initial begin
    $dumpfile("D_latch.vcd");
    $dumpvars(0, L1);
    #2 enable = 0;
    #8 D = 0;
    #10 D = 1;
    #10 enable = 1;
    #10 D = 0;
    #10 D = 1;
    #10 enable = 0;
    #10 D = 0;
    #10 D = 1;
    #10 $finish;
  end
  initial $monitor("D=%b Enable=%b Q=%b", D, enable, Q);
endmodule

LAB08/build/D_latch.vcd
$date
	Fri Dec 02 01:32:58 2022
$end
$version
	Icarus Verilog
$end
$timescale
	1s
$end
$scope module t_D_latch $end
$scope module L1 $end
$var wire 1 ! D $end
$var wire 1 " enable $end
$var reg 1 # Q $end
$upscope $end
$upscope $end
$enddefinitions $end
#0
$dumpvars
x#
x"
x!
$end
#2
0"
#10
0!
#20
1!
#30
1#
1"
#40
0#
0!
#50
1#
1!
#60
0"
#70
0!
#80
1!
